README.md
setup.cfg
setup.py
exploratory/__init__.py
exploratory/exploratory.py
exploratory.egg-info/PKG-INFO
exploratory.egg-info/SOURCES.txt
exploratory.egg-info/dependency_links.txt
exploratory.egg-info/requires.txt
exploratory.egg-info/top_level.txt