Metadata-Version: 2.1
Name: exploratory
Version: 3.4.8
Summary: Exploratory Data Analysis
Home-page: https://github.com/Abhilash-MS/exploratory
Author: Ram <kakarlaramcharan@gmail.com>, Abhilash <abhilashmaspalli1996@gmail.com>
License: UNKNOWN
Keywords: python,EDA,PDF,CDF,Summary Statistics,Mean,Median,Mode,Distribution Plot
Platform: UNKNOWN
Classifier: Intended Audience :: Education
Classifier: Programming Language :: Python :: 3
Classifier: License :: OSI Approved :: MIT License
Classifier: Operating System :: OS Independent
